rqutils/__init__.py
rqutils/_types.py
rqutils/math.py
rqutils/paulis.py
rqutils/qprint.py
rqutils-0.1.4.dist-info/LICENSE
rqutils-0.1.4.dist-info/METADATA
rqutils-0.1.4.dist-info/WHEEL
rqutils-0.1.4.dist-info/top_level.txt
rqutils-0.1.4.dist-info/RECORD
