Metadata-Version: 2.1
Name: rqutils
Version: 0.1.4
Summary: Random quantum utilities
Home-page: https://github.com/UTokyo-ICEPP/rqutils
Author: Yutaro Iiyama
Author-email: iiyama@icepp.s.u-tokyo.ac.jp
Project-URL: Bug Tracker, https://github.com/UTokyo-ICEPP/rqutils/issues
Keywords: quantum,physics
Classifier: Programming Language :: Python :: 3
Classifier: License :: OSI Approved :: MIT License
Classifier: Operating System :: OS Independent
Requires-Python: >=3.6
License-File: LICENSE
Requires-Dist: numpy
